{
	"description": {
		"displayName": "TMF Converter Definition",
		"description": "Converter definition file to generate plantuml files for TMF based data files.\nYou can find further informations here:\nhttps://www.tmforum.org/oda/about-open-apis/"
	},
	"defaultOption": "default",
	"options":  [
			{
				"option": "compact",
				"definition": {
					"continueAfterUnhandledObjects": null,
					"groupDetailObjectsTogether": null,
					"hideDuplicateRelations": null,
					"identifyObjectsByTypeAndIdent": null,
					"legendShowInfo": null,
					"legendShowObjectFormats": null,
					"legendShowFileInfos": null,
					"attributeProperties": {
						"operation": "replace",
						"list":  [
								"id",
								"*name",
								"status"
						]
					},
					"objectProperties":  [
					],
					"objectTypeProperties":  [
					],
					"objectTypeRenames":  [
					],
					"objectIdentifierProperties":  [
					],
					"objectTitleProperties":  [
					],
					"objectDetailProperties":  [
					],
					"relationshipProperties":  [
					],
					"relationshipTypeProperties":  [
					],
					"relationshipTypeArrowFormats":  [
					],
					"groupProperties":  [
					],
					"characteristicProperties":  [
					],
					"hiddenProperties":  [
							"contact*"
					],
					"pumlHeaderLines":  [
					],
					"objectFormats": {
						"baseFormat": {
							"objectFilter": [],
							"iconColor": null,
							"skinParams": [],
							"captionShowIdent": null,
							"captionShowTitle": null,
							"captionShowType": null,
							"captionSplitCharacter": null,
							"captionSplitLength": null,
							"showAttributes": null,
							"showCharacteristics": null,
							"showFromRelations": null,
							"showIfEmpty": null,
							"showNullValues": null,
							"showToRelations": null,
							"sortAttributes": null,
							"valueSplitLength": null
						}
					}
				}
			},
			{
				"option": "core",
				"definition": {
					"continueAfterUnhandledObjects": null,
					"groupDetailObjectsTogether": null,
					"hideDuplicateRelations": null,
					"identifyObjectsByTypeAndIdent": null,
					"legendShowInfo": null,
					"legendShowObjectFormats": null,
					"legendShowFileInfos": null,
					"attributeProperties": {
						"operation": "replace",
						"list":  [
								"*"
						]
					},
					"objectProperties": {
						"operation": "replace",
						"list":  [
								"geographicAddress",
								"product",
								"individual",
								"*Party",
								"paymentMethod",
								"account",
								"customer"
						]
					},
					"objectTypeProperties":  [
					],
					"objectTypeRenames":  [
					],
					"objectIdentifierProperties":  [
					],
					"objectTitleProperties":  [
					],
					"objectDetailProperties":  [
					],
					"relationshipProperties":  [
					],
					"relationshipTypeProperties":  [
					],
					"relationshipTypeArrowFormats":  [
					],
					"groupProperties":  [
					],
					"characteristicProperties":  [
					],
					"hiddenProperties":  [
					],
					"pumlHeaderLines":  [
					],
					"objectFormats": {
						"baseFormat": {
							"objectFilter": [],
							"iconColor": null,
							"skinParams": [],
							"captionShowIdent": null,
							"captionShowTitle": null,
							"captionShowType": null,
							"captionSplitCharacter": null,
							"captionSplitLength": null,
							"showAttributes": null,
							"showCharacteristics": null,
							"showFromRelations": null,
							"showIfEmpty": null,
							"showNullValues": null,
							"showToRelations": null,
							"sortAttributes": null,
							"valueSplitLength": null
						}
					}
				}
			},
			{
				"option": "detailed",
				"definition": {
					"continueAfterUnhandledObjects": null,
					"groupDetailObjectsTogether": null,
					"hideDuplicateRelations": null,
					"identifyObjectsByTypeAndIdent": null,
					"legendShowInfo": null,
					"legendShowObjectFormats": null,
					"legendShowFileInfos": null,
					"attributeProperties":  [
							"*"
					],
					"objectProperties":  [
					],
					"objectTypeProperties":  [
					],
					"objectTypeRenames":  [
					],
					"objectIdentifierProperties":  [
					],
					"objectTitleProperties":  [
					],
					"objectDetailProperties":  [
					],
					"relationshipProperties":  [
					],
					"relationshipTypeProperties":  [
					],
					"relationshipTypeArrowFormats":  [
					],
					"groupProperties":  [
					],
					"characteristicProperties":  [
					],
					"hiddenProperties":  [
					],
					"pumlHeaderLines":  [
					],
					"objectFormats": {
						"baseFormat": {
							"objectFilter": [],
							"iconColor": null,
							"skinParams": [],
							"captionShowIdent": null,
							"captionShowTitle": null,
							"captionShowType": null,
							"captionSplitCharacter": null,
							"captionSplitLength": null,
							"showAttributes": null,
							"showCharacteristics": true,
							"showFromRelations": false,
							"showIfEmpty": null,
							"showNullValues": null,
							"showToRelations": true,
							"sortAttributes": null,
							"valueSplitLength": null
						}
					}
				}
			},
			{
				"option": "full",
				"definition": {
					"continueAfterUnhandledObjects": true,
					"groupDetailObjectsTogether": null,
					"hideDuplicateRelations": null,
					"identifyObjectsByTypeAndIdent": null,
					"legendShowInfo": null,
					"legendShowObjectFormats": null,
					"legendShowFileInfos": null,
					"attributeProperties":  [
							"*"
					],
					"objectProperties": {
						"operation": "replace",
						"list":  [
								{"objectName": "*","generateWithoutIdentifier": "true"}
						]
					},
					"objectTypeProperties":  [
					],
					"objectTypeRenames":  [
					],
					"objectIdentifierProperties":  [
					],
					"objectTitleProperties":  [
					],
					"objectDetailProperties":  [
					],
					"relationshipProperties":  [
					],
					"relationshipTypeProperties":  [
					],
					"relationshipTypeArrowFormats":  [
					],
					"groupProperties":  [
					],
					"characteristicProperties":  [
					],
					"hiddenProperties":  [
					],
					"pumlHeaderLines":  [
					],
					"objectFormats": {
						"baseFormat": {
							"objectFilter": [],
							"iconColor": null,
							"skinParams": [],
							"captionShowIdent": null,
							"captionShowTitle": null,
							"captionShowType": null,
							"captionSplitCharacter": null,
							"captionSplitLength": null,
							"showAttributes": null,
							"showCharacteristics": true,
							"showFromRelations": true,
							"showIfEmpty": true,
							"showNullValues": null,
							"showToRelations": true,
							"sortAttributes": null,
							"valueSplitLength": null
						}
					}
				}
			},
			{
				"option": "product",
				"definition": {
					"continueAfterUnhandledObjects": null,
					"groupDetailObjectsTogether": null,
					"hideDuplicateRelations": null,
					"identifyObjectsByTypeAndIdent": null,
					"legendShowInfo": null,
					"legendShowObjectFormats": null,
					"legendShowFileInfos": null,
					"attributeProperties": {
						"operation": "replace",
						"list":  [
								"id",
								"*name",
								"status"
						]
					},
					"objectProperties": {
						"operation": "replace",
						"list":  [
								"product",
								"customer"
						]
					},
					"objectTypeProperties":  [
					],
					"objectTypeRenames":  [
					],
					"objectIdentifierProperties":  [
					],
					"objectTitleProperties":  [
					],
					"objectDetailProperties": {
						"operation": "replace",
						"list":  [
						]
					},
					"relationshipProperties":  [
					],
					"relationshipTypeProperties":  [
					],
					"relationshipTypeArrowFormats":  [
					],
					"groupProperties":  [
					],
					"characteristicProperties":  [
					],
					"hiddenProperties":  [
					],
					"pumlHeaderLines":  [
					],
					"objectFormats": {
						"baseFormat": {
							"objectFilter": [],
							"iconColor": null,
							"skinParams": [],
							"captionShowIdent": null,
							"captionShowTitle": null,
							"captionShowType": null,
							"captionSplitCharacter": null,
							"captionSplitLength": null,
							"showAttributes": null,
							"showCharacteristics": false,
							"showFromRelations": false,
							"showIfEmpty": null,
							"showNullValues": null,
							"showToRelations": false,
							"sortAttributes": null,
							"valueSplitLength": null
						}
					}
				}
			},
			{
				"option": "product-detail",
				"definition": {
					"continueAfterUnhandledObjects": null,
					"groupDetailObjectsTogether": null,
					"hideDuplicateRelations": null,
					"identifyObjectsByTypeAndIdent": null,
					"legendShowInfo": null,
					"legendShowObjectFormats": null,
					"legendShowFileInfos": null,
					"attributeProperties": {
						"operation": "replace",
						"list":  [
								"*"
						]
					},
					"objectProperties": {
						"operation": "replace",
						"list":  [
								"product",
								"productPrice",
								"customer"
						]
					},
					"objectTypeProperties":  [
					],
					"objectTypeRenames":  [
					],
					"objectIdentifierProperties":  [
					],
					"objectTitleProperties":  [
					],
					"objectDetailProperties": {
						"operation": "replace",
						"list":  [
						]
					},
					"relationshipProperties":  [
					],
					"relationshipTypeProperties":  [
					],
					"relationshipTypeArrowFormats":  [
					],
					"groupProperties":  [
					],
					"characteristicProperties":  [
					],
					"hiddenProperties":  [
					],
					"pumlHeaderLines":  [
					],
					"objectFormats": {
						"baseFormat": {
							"objectFilter": [],
							"iconColor": null,
							"skinParams": [],
							"captionShowIdent": null,
							"captionShowTitle": null,
							"captionShowType": null,
							"captionSplitCharacter": null,
							"captionSplitLength": null,
							"showAttributes": null,
							"showCharacteristics": null,
							"showFromRelations": null,
							"showIfEmpty": null,
							"showNullValues": null,
							"showToRelations": null,
							"sortAttributes": null,
							"valueSplitLength": null
						}
					}
				}
			},
			{
				"option": "relations",
				"definition": {
					"continueAfterUnhandledObjects": true,
					"groupDetailObjectsTogether": null,
					"hideDuplicateRelations": null,
					"identifyObjectsByTypeAndIdent": null,
					"legendShowInfo": null,
					"legendShowObjectFormats": null,
					"legendShowFileInfos": null,
					"attributeProperties": {
						"operation": "replace",
						"list":  [
								"id",
								"*name",
								"status"
						]
					},
					"objectProperties": {
						"operation": "replace",
						"list":  [
								{"objectName": "*","generateWithoutIdentifier": "true"}
						]
					},
					"objectTypeProperties":  [
					],
					"objectTypeRenames":  [
					],
					"objectIdentifierProperties":  [
					],
					"objectTitleProperties":  [
					],
					"objectDetailProperties":  [
					],
					"relationshipProperties":  [
					],
					"relationshipTypeProperties":  [
					],
					"relationshipTypeArrowFormats":  [
					],
					"groupProperties":  [
					],
					"characteristicProperties":  [
					],
					"hiddenProperties":  [
							"appliedTax"
					],
					"pumlHeaderLines":  [
					],
					"objectFormats": {
						"baseFormat": {
							"objectFilter": [],
							"iconColor": null,
							"skinParams": [],
							"captionShowIdent": null,
							"captionShowTitle": null,
							"captionShowType": null,
							"captionSplitCharacter": null,
							"captionSplitLength": null,
							"showAttributes": null,
							"showCharacteristics": false,
							"showFromRelations": true,
							"showIfEmpty": true,
							"showNullValues": null,
							"showToRelations": true,
							"sortAttributes": null,
							"valueSplitLength": null
						}
					}
				}
			},
			{
				"option": "short",
				"definition": {
					"continueAfterUnhandledObjects": null,
					"groupDetailObjectsTogether": null,
					"hideDuplicateRelations": null,
					"identifyObjectsByTypeAndIdent": null,
					"legendShowInfo": null,
					"legendShowObjectFormats": null,
					"legendShowFileInfos": null,
					"attributeProperties": {
						"operation": "replace",
						"list":  [
								"id",
								"*name",
								"status"
						]
					},
					"objectProperties":  [
					],
					"objectTypeProperties":  [
					],
					"objectTypeRenames":  [
					],
					"objectIdentifierProperties":  [
					],
					"objectTitleProperties":  [
					],
					"objectDetailProperties":  [
					],
					"relationshipProperties":  [
					],
					"relationshipTypeProperties":  [
					],
					"relationshipTypeArrowFormats":  [
					],
					"groupProperties":  [
					],
					"characteristicProperties":  [
					],
					"hiddenProperties":  [
							"contactMedium.characteristic"
					],
					"pumlHeaderLines":  [
					],
					"objectFormats": {
						"baseFormat": {
							"objectFilter": [],
							"iconColor": null,
							"skinParams": [],
							"captionShowIdent": null,
							"captionShowTitle": null,
							"captionShowType": null,
							"captionSplitCharacter": null,
							"captionSplitLength": null,
							"showAttributes": null,
							"showCharacteristics": false,
							"showFromRelations": false,
							"showIfEmpty": null,
							"showNullValues": null,
							"showToRelations": false,
							"sortAttributes": null,
							"valueSplitLength": null
						}
					}
				}
			}
	],
	"baseOption": {
		"continueAfterUnhandledObjects": false,
		"groupDetailObjectsTogether": false,
		"hideDuplicateRelations": true,
		"identifyObjectsByTypeAndIdent": false,
		"legendShowInfo": true,
		"legendShowObjectFormats": true,
		"legendShowFileInfos": true,
		"attributeProperties":  [
				"characteristic.*",
				"id",
				"*name",
				"status",
				"state",
				"role",
				"type",
				"birthDate",
				"ratingType",
				"preferred",
				"*Type",
				"*SubType",
				"value",
				"mediumType",
				"@referredType"
		],
		"objectProperties":  [
				"appointment",
				"troubleTicket",
				"partyInteraction",
				"interactionItem",
				"attachment",
				"UrbanPropertyAddress",
				"financialAccount",
				"billingAccount",
				"product",
				"quote",
				"quoteItem",
				"productOrder",
				"productOrderItem",
				"orderItem",
				"itemPrice",
				"productPrice",
				"productOffering",
				"agreement",
				"agreementItem",
				"paymentMethod",
				"individual",
				"organization",
				"customer",
				"engagedParty",
				"relatedParty",
				"contact",
				"appliedCustomerBillingRate",
				"geographicAddress",
				"account",
				"party",
				"customerEntity"
		],
		"objectTypeProperties":  [
				"refType",
				"externalIdentifierType",
				"@referredType",
				"@type",
				"deserializationType"
		],
		"objectTypeRenames":  [
				"compositeProduct=product",
				"defaultPaymentMethod=paymentMethod",
				"UrbanPropertyAddress=geographicAddress",
				"place=geographicAddress",
				"email=contactMedium",
				"telephone=contactMedium",
				"postalAddress=contactMedium",
				"originalaccount=account",
				"customerEntity=customer"
		],
		"objectIdentifierProperties":  [
				"id",
				"ticketId",
				"referenceId"
		],
		"objectTitleProperties":  [
				"fullName",
				"name",
				"characteristic.contactType",
				"contactMedium.mediumType"
		],
		"objectDetailProperties":  [
				"contactMedium",
				"totalBalance",
				"product.productTerm",
				"orderItem.itemTerm",
				"xpriceAlteration"
		],
		"relationshipProperties":  [
				"relatedParty",
				"engagedParty",
				"relatedEntity",
				"place",
				"productRelationship"
		],
		"relationshipTypeProperties":  [
				"role",
				"type",
				"relationshipType",
				"characteristic.contactType",
				"contactMedium.mediumType"
		],
		"relationshipTypeArrowFormats":  [
				"relatedparty=[dotted]",
				"relatedparty.customer=[#blue,dotted]",
				"relatedparty.individual=[#lightgrey,dotted]",
				"relatedparty.organisation=[#grey,dotted]",
				"engagedparty=[dotted]",
				"engagedparty.individual=[#lightgrey,dotted]",
				"engagedparty.organisation=[#grey,dotted]",
				"productrelationship=[dashed]",
				"productrelationship.dependson=[#blue,dashed]",
				"productrelationship.commercialrelation=[#gold,dashed]",
				"productrelationship.subscriptionrelation=[#green,dashed]",
				"productrelationship.orderitem=[#orange,dashed]"
		],
		"groupProperties":  [
				"product.productOrder",
				"individual.*",
				"contactmedium",
				"financialaccount",
				"historyRecord",
				"productOrder.orderItem",
				"relatedParty",
				"itemPrice",
				"paymentMethod",
				"geographicAddress",
				"customer",
				"billingAccount"
		],
		"characteristicProperties":  [
				{"parentProperty": "metadata", "type": "list", "propertyList": ["name", "value", "*"]},
				{"parentProperty": "modifyReason", "type": "list", "propertyList": ["name", "action", "*"]},
				{"parentProperty": "stateDate", "type": "list", "propertyList": ["effectiveDate", "*"]},
				{"parentProperty": "businessActivity", "type": "list", "propertyList": ["effectiveDate", "name", "*"]},
				{"parentProperty": "individual.externalReference", "type": "list", "propertyList": ["externalReferenceType", "name", "id"]},
				"details",
				"extensions",
				"size",
				"interactionDate",
				"itemDate",
				"validFor",
				{"parentProperty": "channel", "type": "list", "propertyList": ["name", "id"]},
				{"parentProperty": "productOfferingCharacteristic", "type": "list", "propertyList": ["name", "value", "*"]},
				{"parentProperty": "product.characteristic", "type": "list", "propertyList": ["name", "value", "*"]},
				{"parentProperty": "orderItem.characteristic", "type": "list", "propertyList": ["name", "value", "*"]},
				{"parentProperty": "productCharacteristic", "type": "list", "propertyList": ["name", "value", "*"]},
				{"parentProperty": "customer.characteristic", "type": "list", "propertyList": ["name", "value", "*"]},
				{"parentProperty": "partyCharacteristic", "type": "list", "propertyList": ["name", "value", "*"]},
				{"parentProperty": "troubleticket.characteristic", "type": "list", "propertyList": ["name", "value", "*"]},
				{"parentProperty": "troubleticket.statusChange", "type": "list", "propertyList": ["changeDate", "status", "*"]},
				{"parentProperty": "note", "type": "list", "propertyList": ["date", "author", "text", "*"]},
				{"parentProperty": "historyChange", "type": "list", "propertyList": ["operation", "path", "oldValue", "newValue", "*"]},
				"tax*Amount",
				"exemptAmount",
				"dutyFreeAmount",
				"otherName",
				"duration",
				"quantity",
				"amount",
				"presentationMedia",
				"format",
				"cycleSpecification",
				"periodCoverage",
				"taxDefinition",
				"immediatePayOption",
				"priceOverride",
				"activitySource",
				"businessProperties",
				"elapsedDuration",
				"remainingDuration",
				"price",
				"standalonePrice",
				"finalPrice",
				"priceAlteration",
				"itemTotalPrice",
				"orderTotalPrice",
				"billStructure",
				"appliedTax",
				{"parentProperty": "contactMedium.characteristic", "type": "record", "propertyList": "-@type"},
				{"parentProperty": "externalIdentifier", "type": "list", "propertyList": ["externalIdentifierType", "type", "id", "owner", "*"]}
		],
		"hiddenProperties":  [
				"characteristicMetadata",
				"href",
				"@referredType",
				"engagedParty.type",
				"relatedParty.role",
				"relatedParty.validFor",
				"relatedParty.@referredType",
				"originalResource",
				"appliedTax"
		],
		"pumlHeaderLines":  [
				"hide stereotype",
				"'left to right direction",
				"'skinparam linetype polyline",
				"'skinparam linetype ortho",
				"skinparam HeaderFontSize 18",
				"skinparam FooterFontSize 18"
		],
		"objectFormats": {
			"baseFormat": {
				"objectFilter": [],
				"iconColor": null,
				"skinParams": ["BackgroundColor=STRATEGY"],
				"captionShowIdent": true,
				"captionShowTitle": true,
				"captionShowType": true,
				"captionSplitCharacter": "_",
				"captionSplitLength": 20,
				"showAttributes": true,
				"showCharacteristics": true,
				"showFromRelations": false,
				"showIfEmpty": false,
				"showNullValues": null,
				"showToRelations": false,
				"sortAttributes": true,
				"valueSplitLength": 50
			},
			"formats":  [
					{
						"formatName": "partyInteraction",
						"definition": {
							"objectFilter": [
								"partyInteraction",
								"interactionItem",
								"attachment"
							],
							"iconColor": "blue",
							"skinParams": ["BackgroundColor=dodgerBlue"]
						}
					},
					{
						"formatName": "troubleTicket",
						"definition": {
							"objectFilter": [
								"troubleTicket",
								"appointment",
								"calenderEvent",
								"workorder",
								"ticketSpec",
								"workItem",
								"troubleTicket.historyRecord"
							],
							"iconColor": "Cornflowerblue",
							"skinParams": ["BackgroundColor=deepskyBlue"]
						}
					},
					{
						"formatName": "productOffering",
						"definition": {
							"objectFilter": ["productOffering"],
							"iconColor": "IndianRed",
							"skinParams": ["BackgroundColor=DarkSalmon"]
						}
					},
					{
						"formatName": "productOrder",
						"definition": {
							"objectFilter": [
								"productOrder",
								"orderItem",
								"itemTerm",
								"itemPrice",
								"quote",
								"quoteItem",
								"orderTotalPrice"
							],
							"iconColor": "DarkGreen",
							"skinParams": ["BackgroundColor=Lime"]
						}
					},
					{
						"formatName": "product",
						"definition": {
							"objectFilter": [
								"product*",
								"Price",
								"appliedCustomerBillingRate"
							],
							"iconColor": "Green",
							"skinParams": ["BackgroundColor=LightGreen"]
						}
					},
					{
						"formatName": "customer",
						"definition": {
							"objectFilter": ["customer"],
							"iconColor": "red",
							"skinParams": ["BackgroundColor=orangered"]
						}
					},
					{
						"formatName": "agreement",
						"definition": {
							"objectFilter": [
								"agreement",
								"agreementItem",
								"commitment"
							],
							"iconColor": "Crimson",
							"skinParams": ["BackgroundColor=red"]
						}
					},
					{
						"formatName": "contact",
						"definition": {
							"objectFilter": ["contact*"],
							"iconColor": "DeepSkyBlue",
							"skinParams": ["BackgroundColor=LightSkyBlue"]
						}
					},
					{
						"formatName": "geographicAddress",
						"definition": {
							"objectFilter": [
								"geographicAddress",
								"geographicSubAddress",
								"UrbanPropertyAddress",
								"place"
							],
							"iconColor": "darkcyan",
							"skinParams": ["BackgroundColor=cyan"]
						}
					},
					{
						"formatName": "billingaccount",
						"definition": {
							"objectFilter": [
								"billingAccount",
								"billStructure",
								"account"
							],
							"iconColor": "purple",
							"skinParams": ["BackgroundColor=plum"]
						}
					},
					{
						"formatName": "financialaccount",
						"definition": {
							"objectFilter": ["financialAccount"],
							"iconColor": "purple",
							"skinParams": ["BackgroundColor=DeepPink"]
						}
					},
					{
						"formatName": "paymentMethod",
						"definition": {
							"objectFilter": ["paymentMethod"],
							"iconColor": "orange",
							"skinParams": ["BackgroundColor=orange"]
						}
					},
					{
						"formatName": "party",
						"definition": {
							"objectFilter": [
								"party",
								"relatedParty",
								"engagedParty",
								"organization",
								"individual",
								"workForceIndividual"
							],
							"iconColor": "grey",
							"skinParams": ["BackgroundColor=lightgrey"]
						}
					}
			]
		}
	}
}
